mailhandler/__init__.py
mailhandler/adapters.py
mailhandler/core.py
mailhandler/exceptions.py
mailhandler/bulk/__init__.py
mailhandler/bulk/adapters.py
mailhandler/tracking/__init__.py
mailhandler/tracking/adapters.py
mailhandler/transactional/__init__.py
mailhandler/transactional/adapters.py
mailhandler-0.0.5.dist-info/LICENSE
mailhandler-0.0.5.dist-info/METADATA
mailhandler-0.0.5.dist-info/WHEEL
mailhandler-0.0.5.dist-info/top_level.txt
mailhandler-0.0.5.dist-info/RECORD
